django_advanced_password_validators/__init__.py
django_advanced_password_validators/validators/__init__.py
django_advanced_password_validators/validators/password_validators.py
django_advanced_password_validators-0.1.dist-info/LICENSE
django_advanced_password_validators-0.1.dist-info/METADATA
django_advanced_password_validators-0.1.dist-info/WHEEL
django_advanced_password_validators-0.1.dist-info/top_level.txt
django_advanced_password_validators-0.1.dist-info/RECORD
