Metadata-Version: 2.1
Name: django_advanced_password_validators
Version: 0.1
Summary: A Django package for custom password validation.
Home-page: https://github.com/shanathvemula/django_advanced_password_validators
Author: Shanath Kumar Vemula
Author-email: shanath1213@gmail.com
Classifier: Framework :: Django
Classifier: Programming Language :: Python :: 3
Classifier: Operating System :: OS Independent
License-File: LICENSE
Requires-Dist: django >=3.0
